{
  "name": "Ubuntu",
  "image": "mcr.microsoft.com/devcontainers/base:noble",
  "features": {
    "ghcr.io/devcontainers/features/git-lfs:1": {},
    "ghcr.io/devcontainers/features/node:1": {
      "version": "22.22.0"
    }
  },
  "postCreateCommand": {
    "npm-check-updates": "npm install -g npm-check-updates"
  },
  "customizations": {
    "vscode": {
      "extensions": [
        "editorconfig.editorconfig",
        "github.vscode-github-actions",
        "redhat.vscode-yaml",
        "redhat.vscode-xml",
        "styled-components.vscode-styled-components",
        "vitest.explorer"
      ],
      "settings": {
        "redhat.telemetry.enabled": false
      }
    }
  }
}
